{"f6HMQ07aUHMJHTfeiwwAxQ==":"bonus-new-member-pasti-dapet-1836x918.png","oE/tsjuSWYtB/pFHaDPXQQ==":"main-slot-modal-receh-1836x918.png","LEqJtXl8GQZQkG7WrSj6WQ==":"cara-main-slot-anti-kalah-1836x918.png","O4PWaa+yTTxr9H/kT0k1/w==":"gates-of-olympus-home-300x300.png","7kAuf4uEFM0Rb00LuAEr9Q==":"sweet-bonanza-home-300x300.png","qhE+A4vLQWhGHHblvvHsmw==":"bounty-gold-home-300x300.png","CNTHJ4Vvl+l6BvBFr6jRfA==":"hot-fiesta-home-300x300.png","d0ubDYEorsepwyTOQH4ePg==":"background4.jpg","pAL/J2cy4hOWdeKP9a1fjw==":"magicians-secret-339x180.png","QyOnNuT/UEERbOh0Rf+Fkg==":"tiger-treasures-339x180.png","mAZCqRwettL8WtbOLVq2rw==":"super-x-339x180.png","F1P22M6iU1NaMv5EHvCDdw==":"fortune-of-giza-350x221.png","5lxKFK8bTVrIP/9L8MG2tA==":"background2.jpg","WwGymgkFxYTgVanzQa31hg==":"about-us-400x279.png","dAJavstQ+squdXyCHilVOw==":"raja9-80x43.png","8nNWbBIb5Ceq7Skpfp/zVw==":"basegame_bg1-1000x562.png","XD3dTxJVD4/+WEfYuTLKqg==":"popup.jpg","hE450m8IcCLGC0IuUabWLg==":"2021-10-24t13_59_31.078z_banner-4-1266x475.jpg","df+NYp+1uv2nSIWnG2TV7Q==":"background2-1.jpg","EiLQMLgEgcH1WXCLoLOx2g==":"2022-04-09t07_48_49.663z_banner-1-1600x600.jpg","y3RbrnfxXqmegef9AtbGKA==":"2022-04-09t07_48_58.007z_banner-2-1600x600.jpg","QkNQ0hudL5cMUAlMCjfjAg==":"2022-04-09t07_49_08.209z_banner-3-1600x600.jpg","ctXXczGSoXLGQ/2tvwBEcQ==":"pp-starlight-guardian-1362x512.png","z+Om7KmdI7gGTHBpf/2M+w==":"spade-summer-tournament-1362x512.jpg","911X7bM4yT2Mobv6BsMc+g==":"background8.jpg","BJGeWl4Ry4cEoD7v557Uqw==":"5-lions-megaways-200x200.jpg","PChH2oImRwRjz98cZlWR9w==":"aztec-gems-200x200.jpg","rukOuMNtCTt3KB/Redb83Q==":"wild-west-gold-200x200.jpg","qAUyAMiet76CnbEFK20ulg==":"wild-booster-200x200.jpg","447HIHMZveZIGqlYGAkBnw==":"voodoo-magic-200x200.jpg","cy6W+8Je08a7cGz5ppj6WA==":"aztec-gems-deluxe-200x200.jpg","7G4kGrJUmYpKGI/RQduX9A==":"christmas-big-bass-bonanza-200x200.jpg","IetOsWF6SKGUo1FxjooFvw==":"christmas-carol-megaways-200x200.jpg","bgspnjVVWa9P/d+NyhWMyA==":"caishen-wins-200x200.jpg","xbGJXICXJskFeM+Ff/iXvA==":"legendary-monkey-kings-200x200.jpg","J0LyukdpzH4O5bfkhbTSwg==":"thai-river-wonders-200x200.jpg","KlMdoMRa31AgETwFAJv+cg==":"queen-of-bounty-200x200.jpg","4XJBObCRwfxG82JoGjTvpA==":"mahjong-ways-2-200x200.jpg","uqxjwRjBEa6wv/AZTSQFxw==":"gem-saviour-conquest-200x200.jpg","hgIxg6/Fz5B2U6ACW8fTmQ==":"frogs-and-flies-200x200.jpg","gOtbnBcfG8kwxOHaCyilNw==":"crystal-crater-200x200.jpg","IA1RDIL4B04afJ6KhEZn4g==":"ganesh-blessing-200x200.jpg","Vpa6tSoovrOpPjxMGsFQLA==":"dragon-orb-200x200.jpg","2vuG33289WoWg4j7pIQI3g==":"cherry-love-200x200.jpg","HzlaGbcnItkHTmZc2cpi4w==":"panda-pursuit-200x200.jpg","JwYOAUleDbpFlTaUL0JDmQ==":"mystic-fortune-200x200.jpg","+JRpex7WwyJVrXT+4aWq4A==":"christmas-gift-rush-200x200.jpg","7Z+iWlSltPpaB7AnVE6jLA==":"totem-towers-200x200.jpg","skmOJbFBfaVeUCSVSPu8EA==":"nuwa-200x200.jpg","0PzjJVdbp6Dfj5b3LgcmRA==":"new-years-bash-200x200.jpg","vw/j7No7JE2fVLILtsV9nw==":"lucky-fortune-cat-200x200.jpg","d4jVpaBCbz0CoNgNk46g6w==":"magical-lamp-200x200.jpg","YjgyEn+hV8LCG18JXj85Gw==":"gold-panther-200x200.jpg","AekJgOLK+RzGsj5gEWjqxA==":"three-lucky-stars-200x200.jpg","JD/1GEGxemTSANYaiAX9Ng==":"sweet-bakery-200x200.jpg","XfQ1t6HTwI+KB0dJ+44ysg==":"legendary-beast-saga-200x200.jpg","PJGPqh7tbIDAgD5V1IIvcA==":"prosperity-god-200x200.jpg","22O/2GwoNU+fbqWi52MoJQ==":"10000-wishes-200x200.jpg","YszdFM9SUSFWBAg3fuAntA==":"break-away-deluxe-200x200.jpg","dHafkru5QJCbomghKstaJg==":"immortal-romance-200x200.jpg","PeraOISK0QMPJZ1tJBuY5Q==":"basketball-star-wilds-200x200.jpg","4S5lmsUuRfnVoXxHdmaD0A==":"diamond-king-jackpots-200x200.jpg","RyfPDNAk4k92/ze4uNg+gQ==":"9-masks-of-fire-200x200.jpg","HOfJlinXJcN76SL8LAmiGA==":"dancing-papa-200x200.jpg","wRU07N/e/QDM6aZdEpY43A==":"moonlight-treasure-200x200.jpg","oNfaStd0S+CiqB9NvVKCQg==":"lucky-miner-200x200.jpg","Ub6G8K2OZK+0nMTxOl0ggA==":"napoleon-200x200.jpg","Y4BotxATVV0gs9RRsUEIyg==":"crystal-realm-200x200.jpg","IuWa9JOwkY9fhd9UBWz6Eg==":"blossom-wealth-200x200.jpg","CAtmHNp5aPuM4BRJd5Af9g==":"gates-of-olympus-gameplay-696x418.png","IzstI8p+NvVVer3dUSVcKg==":"wild-west-gold-gameplay-696x418.png","2yhT3ZnYNX5miZ8ZAR+t8w==":"sweet-bonanza-gameplay-696x418.png","NKz4Rzqsh1qpZbkGtUxy8Q==":"01.jpg","gRKY9Vm0EryhGEJFv0mBuw==":"starlight-princess-gameplay-696x418.jpg","ifvBTVGHGhAsA5lcLM+q9w==":"wild-west-gold-megaways-gameplay-696x418.jpg","mYE1tWk2z7k92i18+qz4Qg==":"hot-fiesta-gameplay-696x418.jpg","dVziMDQF2C5g2SzZnv2/xA==":"magicians-secret-gameplay-696x418.jpg","qnj7Bp4JWjAfTbUzEPwGAg==":"aztec-gemz-deluxe-gameplay-696x418.jpg","/AvE3u8Z8QKh5jE/Eg+yvQ==":"emperor-caishen-gameplay-696x418.jpg","tkF7k2k1awItMKebua31Iw==":"tiger-treasures-gameplay-696x418.png","QYZxYHXyuOqAjVfO5N4B1Q==":"super-x-gameplay-696x418.png","8AzaipeYGdfcoE5sUvrQGg==":"fortune-of-giza-gameplay-696x418.png","vRBLYYs9CizVQReWTzJC4A==":"mask-carnival-gameplay-696x418.png","mNr3t5vxzrR4M2AN3Hle9A==":"big-bass-bonanza-megaways-gameplay-696x418.png","jA7aEdL8CqxmzA3Pvi76xg==":"hockey-attack-gameplay-696x418.png","+vionoPSTFaAfnaoeLwSMQ==":"bounty-gold-gameplay-696x418.png","PUFisQBCWnlFIA2Rfnn+ag==":"bubble-pop-gameplay-696x418.png","xjFWEq9T6QPgJVJbIX3lSA==":"book-of-fallen-gameplay-696x418.png","Ic6J9JXX1/YDy6kBPqU6BA==":"christmas-big-bass-bonanza-gameplay-696x418.jpg","xB/d14saGY3P0PPqKKWlTw==":"santas-wonderland-gameplay-696x418.png","molQIqDE94EtnUZl8z7buA==":"big-juan-gameplay-696x418.png","D5PP1z+8YrktfFromQ/aNA==":"john-hunter-the-quest-for-bermuda-riches-gameplay-696x418.png","thF8OojBN5DFA1nk6d3VPw==":"star-pirates-code-gameplay-696x418.png","cuqRQlklMUgREPTsp6BrRg==":"fruit-party-2-gameplay-696x418.png","UsjEHfPPQKyUKl8c6qSUMQ==":"gates-of-olympus-339x180.png","l38rLJqVMEQUcoydsG5/Ew==":"gates-of-olympus-gameplay-1000x600.png","QQx3IyXdey6CEM9e+W4nTw==":"top-12-permainan-slot-terbaik-pragmatic-play-versi-btv168-696x418.jpg","vGycBZcNcGubTee7X36wAQ==":"pentingnya-mencoba-demo-slot-online-sebelum-bertaruh-696x418.jpg","g0Hyd0E8wvvSFQcBgdF4pg==":"panduan-cara-bermain-baccarat-online-dari-live-casino-696x418.jpg","vOWNlQa4xwVVAVpvYhGJBA==":"beberapa-istilah-yang-sering-digunakan-para-pemain-slot-online-696x418.jpg","WDv6sysUD7+mixHWnZF8Iw==":"siapa-lebih-pintar-manusia-vs-mesin-atau-mesin-vs-mesin-696x418.jpg","cdgZ5k6eox0YSwyD5AEiBw==":"slot88-provider-slot-online-paling-bergensi-yang-pernah-ada-696x418.jpg","xV9FTQ/duFADdpwGdsHrBQ==":"mengenal-cara-bermain-poker-online-dan-bagaimana-menguasainya-696x418.jpg","kDYY+p42NsohGdmNDKmmfA==":"domino-qiu-qiu-permainan-seru-sepanjang-masa-696x418.jpg","D+ACdnLhDvySBWuakysB5w==":"mengenal-sang-jagoan-slot-pragmatic-play-696x418.jpg","zMc8jEoj3hJfg7m/l+9Whw==":"top-10-provider-slot-online-terbaik-di-indonesia-696x418.jpg","HKll1jp72nKyG2p4d2u2iQ==":"game-terbaik-yang-harus-dicoba-dari-pgsoft-696x418.jpg","/tECR0owU3YW2jT8wxD1cQ==":"mengenal-pg-soft-provider-slot-online-paling-kekinian-696x418.jpg","BcTKJXNO257dZwVF8QyyOw==":"top-12-permainan-slot-terbaik-pragmatic-play-versi-btv168-700x420.jpg","oRykAiO0rUD++7AmPeEwUg==":"background1.jpg","n1dx+NZv3qks526xC0hZ5Q==":"background13.jpg","VL4jhVizy+r9GU+9QBt4Vw==":"mengakali-menang-judi-online-dengan-bet-kecil-696x418.jpg","QT7+AVk68lpT63BrELRFrg==":"cara-bermain-gates-of-olympus-1-696x418.jpg","RQTBUd6SxQwdBPZpMdRmdQ==":"cara-bermain-sweet-bonanza-1-696x418.jpg","icpXhVZS90ifpHe6F2xdVQ==":"teknik-rahasia-bermain-slot-online-jitu-yang-jarang-dimengerti-orang-696x418.jpg","1XFO8li4/Rrx4dG6ngiJvg==":"10-daftar-game-slot-pragmatic-play-yang-harus-dihindari-696x418.jpg","GH3IsSDEP5sflfuQ5eCE/Q==":"tips-jitu-bermain-slot-online-sebagai-pemula-696x418.jpg","IKNpLhHGkBPzs41mcJWDKw==":"mengakali-menang-judi-online-dengan-bet-kecil-700x420.jpg"}